sense_html/__init__.py
sense_html/change_info.py
sense_html/test.py
sense_html/test_all.py
sense_html/text_etl.py
sense_html-2.4.0.dist-info/METADATA
sense_html-2.4.0.dist-info/WHEEL
sense_html-2.4.0.dist-info/top_level.txt
sense_html-2.4.0.dist-info/RECORD
